west/__init__.py
west/__main__.py
west/commands.py
west/configuration.py
west/log.py
west/manifest-schema.yml
west/manifest.py
west/py.typed
west/util.py
west/version.py
west/west-commands-schema.yml
west/app/__init__.py
west/app/config.py
west/app/main.py
west/app/project.py
west-1.3.0.dist-info/LICENSE
west-1.3.0.dist-info/METADATA
west-1.3.0.dist-info/WHEEL
west-1.3.0.dist-info/entry_points.txt
west-1.3.0.dist-info/top_level.txt
west-1.3.0.dist-info/RECORD
