Metadata-Version: 2.1
Name: west
Version: 1.3.0
Summary: Zephyr RTOS Project meta-tool
Author-email: Zephyr Project <devel@lists.zephyrproject.org>
License:                                  Apache License
Project-URL: Homepage, https://github.com/zephyrproject-rtos/west
Classifier: Programming Language :: Python :: 3
Classifier: License :: OSI Approved :: Apache Software License
Classifier: Operating System :: POSIX :: Linux
Classifier: Operating System :: MacOS :: MacOS X
Classifier: Operating System :: Microsoft :: Windows
Requires-Python: >=3.9
License-File: LICENSE
Requires-Dist: colorama
Requires-Dist: PyYAML>=5.1
Requires-Dist: pykwalify
Requires-Dist: setuptools
Requires-Dist: packaging
